beatmachine-3.2.0.dist-info/dependency_links.txt
beatmachine-3.2.0.dist-info/entry_points.txt
beatmachine-3.2.0.dist-info/METADATA
beatmachine-3.2.0.dist-info/top_level.txt
beatmachine-3.2.0.dist-info/WHEEL
beatmachine/beats.py
beatmachine/dump_schema.py
beatmachine/loader.py
beatmachine/__init__.py
beatmachine/__main__.py
beatmachine/effects/base.py
beatmachine/effects/periodic.py
beatmachine/effects/temporal.py
beatmachine/effects/__init__.py
beatmachine-3.2.0.dist-info/LICENSE
beatmachine-3.2.0.dist-info/RECORD