Metadata-Version: 2.1
Name: beatmachine
Version: 3.2.0
Summary: A library for procedurally remixing songs
Author: dhsavell
Author-email: dhsavell05@gmail.com
License: MIT
Requires-Python: >=3.7
Requires-Dist: black==20.*,>=20.8.0.b1; extra == "dev"
Requires-Dist: bump2version==1.*,>=1.0.0; extra == "dev"
Requires-Dist: deprecation==2.*,>=2.0.0
Requires-Dist: jsonschema==3.*,>=3.2.0
Requires-Dist: madmom
Requires-Dist: numpy==1.*,>=1.20.0
Requires-Dist: parameterized==0.*,>=0.7.1; extra == "dev"
Requires-Dist: pre-commit==1.*,>=1.20.0; extra == "dev"
Requires-Dist: pytest==5.*,>=5.3.5; extra == "dev"
Requires-Dist: rope==0.*,>=0.18.0; extra == "dev"
Requires-Dist: schema==0.*,>=0.7.3
Requires-Dist: soundfile==0.*,>=0.10.3
Requires-Dist: sphinx==2.*,>=2.2.0; extra == "dev"
Requires-Dist: sphinx-rtd-theme==0.*,>=0.5.0; extra == "dev"
Provides-Extra: dev